pipecutter/__init__.py
pipecutter/deps.py
pipecutter/deps_tree.py
pipecutter/interface.py
pipecutter/targets.py
pipecutter-2.0.0.dist-info/LICENSE
pipecutter-2.0.0.dist-info/METADATA
pipecutter-2.0.0.dist-info/WHEEL
pipecutter-2.0.0.dist-info/top_level.txt
pipecutter-2.0.0.dist-info/RECORD
