Metadata-Version: 2.1
Name: pipecutter
Version: 2.0.0
Summary: pipecutter provides a few tools for luigi such that it works better with data science libraries and environments such as pandas, scikit-learn, and Jupyter notebooks.
Home-page: https://github.com/binste/pipecutter
Author: Stefan Binder
License: MIT
Keywords: luigi,spotify,pipeline,plumber,workflow,batch,dependency resolution,jupyter,interactive,targets
Platform: UNKNOWN
Classifier: Intended Audience :: Developers
Classifier: Intended Audience :: System Administrators
Classifier: License :: OSI Approved :: MIT License
Classifier: Programming Language :: Python :: 3.6
Classifier: Programming Language :: Python :: 3.7
Classifier: Development Status :: 5 - Production/Stable
Requires-Python: >=3.6,<3.8
Requires-Dist: pandas (>=0.21)
Requires-Dist: joblib (>=0.11)
Requires-Dist: luigi (>=2.8.5)
Requires-Dist: pyarrow
Provides-Extra: dev
Requires-Dist: black ; extra == 'dev'
Provides-Extra: graphviz
Requires-Dist: graphviz ; extra == 'graphviz'
Provides-Extra: test
Requires-Dist: pytest ; extra == 'test'
Requires-Dist: flake8 ; extra == 'test'
Requires-Dist: mypy ; extra == 'test'
Requires-Dist: black ; extra == 'test'
